ovos_stt_plugin_fasterwhisper/__init__.py
ovos_stt_plugin_fasterwhisper/version.py
ovos_stt_plugin_fasterwhisper-0.4.0.dist-info/licenses/LICENSE
ovos_stt_plugin_fasterwhisper-0.4.0.dist-info/METADATA
ovos_stt_plugin_fasterwhisper-0.4.0.dist-info/WHEEL
ovos_stt_plugin_fasterwhisper-0.4.0.dist-info/entry_points.txt
ovos_stt_plugin_fasterwhisper-0.4.0.dist-info/top_level.txt
ovos_stt_plugin_fasterwhisper-0.4.0.dist-info/zip-safe
ovos_stt_plugin_fasterwhisper-0.4.0.dist-info/RECORD
