Metadata-Version: 2.4
Name: ovos-stt-plugin-fasterwhisper
Version: 0.4.0
Summary: A fasterwhisper stt plugin for mycroft
Home-page: https://github.com/OpenVoiceOS/ovos-stt-plugin-fasterwhisper
Author: JarbasAi
Author-email: jarbasai@mailfence.com
License: Apache-2.0
Keywords: OpenVoiceOS mycroft ovos plugin stt
Classifier: Development Status :: 3 - Alpha
Classifier: Intended Audience :: Developers
Classifier: License :: OSI Approved :: Apache Software License
License-File: LICENSE
Requires-Dist: ovos-plugin-manager<3.0.0,>=2.1.0
Requires-Dist: SpeechRecognition>=3.8.1
Requires-Dist: faster-whisper>=0.10.0
Requires-Dist: requests
Dynamic: author
Dynamic: author-email
Dynamic: classifier
Dynamic: home-page
Dynamic: keywords
Dynamic: license
Dynamic: license-file
Dynamic: requires-dist
Dynamic: summary
